curlify2/__init__.py
curlify2/curlify.py
curlify2-1.0.3.1.dist-info/LICENSE
curlify2-1.0.3.1.dist-info/METADATA
curlify2-1.0.3.1.dist-info/WHEEL
curlify2-1.0.3.1.dist-info/RECORD
