Metadata-Version: 2.1
Name: curlify2
Version: 1.0.3.1
Summary: Library to convert python requests and httpx object to curl command.
Home-page: https://github.com/marcuxyz/curlify2
License: MIT
Keywords: python,curl,requests,curlify,httpx,convert to curl
Author: Marcus Pereira
Author-email: marcus@negros.dev
Requires-Python: >=3.7,<4.0
Classifier: License :: OSI Approved :: MIT License
Classifier: Programming Language :: Python :: 3
Classifier: Programming Language :: Python :: 3.7
Classifier: Programming Language :: Python :: 3.8
Classifier: Programming Language :: Python :: 3.9
Classifier: Programming Language :: Python :: 3.10
Classifier: Programming Language :: Python :: 3.11
Project-URL: Repository, https://github.com/marcuxyz/curlify2
